odoo/addons/partner_delivery_zone_weighing/README.rst
odoo/addons/partner_delivery_zone_weighing/__init__.py
odoo/addons/partner_delivery_zone_weighing/__manifest__.py
odoo/addons/partner_delivery_zone_weighing/i18n/partner_delivery_zone_weighing.pot
odoo/addons/partner_delivery_zone_weighing/readme/CONTRIBUTORS.md
odoo/addons/partner_delivery_zone_weighing/readme/DESCRIPTION.md
odoo/addons/partner_delivery_zone_weighing/static/description/icon.png
odoo/addons/partner_delivery_zone_weighing/static/description/index.html
odoo/addons/partner_delivery_zone_weighing/views/stock_move_views.xml
odoo_addon_partner_delivery_zone_weighing-15.0.1.0.0.2.dist-info/METADATA
odoo_addon_partner_delivery_zone_weighing-15.0.1.0.0.2.dist-info/WHEEL
odoo_addon_partner_delivery_zone_weighing-15.0.1.0.0.2.dist-info/top_level.txt
odoo_addon_partner_delivery_zone_weighing-15.0.1.0.0.2.dist-info/RECORD
